mobius/__init__.py
mobius/config/config_template.yml
mobius/controller/__init__.py
mobius/controller/controller.py
mobius/controller/api/__init__.py
mobius/controller/api/api_client.py
mobius/controller/chi/__init__.py
mobius/controller/chi/chi_client.py
mobius/controller/chi/network.py
mobius/controller/chi/node.py
mobius/controller/chi/slice.py
mobius/controller/fabric/__init__.py
mobius/controller/fabric/fabric_client.py
mobius/controller/util/__init__.py
mobius/controller/util/config.py
mobius/test/__init__.py
mobius/test/controller.py
mobius_py-1.3.1.dist-info/LICENSE
mobius_py-1.3.1.dist-info/WHEEL
mobius_py-1.3.1.dist-info/METADATA
mobius_py-1.3.1.dist-info/RECORD
