Metadata-Version: 2.1
Name: mobius-py
Version: 1.3.1
Summary: Mobius Multi Testbed Framework
Keywords: Mobius Framework,Cloud,FABRIC,Chameleon,MOC
Author-email: Komal Thareja <kthare10@renci.org>
Requires-Python: >=3.9
Classifier: Programming Language :: Python :: 3
Classifier: License :: OSI Approved :: MIT License
Classifier: Operating System :: OS Independent
Requires-Dist: requests
Requires-Dist: paramiko
Requires-Dist: fabrictestbed-extensions==1.5.5
Requires-Dist: python-chi
Requires-Dist: pytest ; extra == "test"
Requires-Dist: flask_testing ; extra == "test"
Requires-Dist: coverage>=4.0.3 ; extra == "test"
Requires-Dist: nose>=1.3.7 ; extra == "test"
Requires-Dist: pluggy>=0.3.1 ; extra == "test"
Requires-Dist: py>=1.4.31 ; extra == "test"
Requires-Dist: randomize>=0.13 ; extra == "test"
Project-URL: Home, https://github.com/RENCI-NRIG/Mobius
Project-URL: Sources, https://github.com/RENCI-NRIG/Mobius-python
Provides-Extra: test
